{
  "info": {
    "name": "TodoApp",
    "description": null,
    "schema": "https://schema.getpostman.com/json/collection/v2.1.0/collection.json"
  },
  "item": [
    {
      "name": "Register",
      "request": {
        "method": "POST",
        "header": [],
        "auth": {
          "type": "noauth"
        },
        "description": "",
        "url": {
          "raw": "http://localhost:8080/auth/register",
          "protocol": "http",
          "host": [
            "localhost:8080"
          ],
          "path": [
            "auth",
            "register"
          ],
          "query": [],
          "variable": []
        },
        "body": {
          "mode": "raw",
          "raw": "{\n  \"name\": \"Cihuy\",\n  \"username\": \"Cihuy\",\n  \"password\": \"123456\"\n}\n\n",
          "options": {
            "raw": {
              "language": "json"
            }
          }
        }
      }
    },
    {
      "name": "Login",
      "request": {
        "method": "POST",
        "header": [],
        "auth": {
          "type": "noauth"
        },
        "description": "",
        "url": {
          "raw": "http://localhost:8080/auth/login",
          "protocol": "http",
          "host": [
            "localhost:8080"
          ],
          "path": [
            "auth",
            "login"
          ],
          "query": [],
          "variable": []
        },
        "body": {
          "mode": "raw",
          "raw": "{\n  \"username\": \"Cihuy\",\n  \"password\": \"123456\" \n}\n",
          "options": {
            "raw": {
              "language": "json"
            }
          }
        }
      }
    },
    {
      "name": "Create",
      "request": {
        "method": "POST",
        "header": [
          {
            "key": "Authorization",
            "value": "Bearer eyJhbGciOiJIUzI1NiJ9.eyJzdWIiOiJDaWh1eSIsImlhdCI6MTc3ODQ2NTU1MiwiZXhwIjoxNzc4NTUxOTUyfQ.0OMRlcasvAX7kFG9WANHfsh1nuzPboF7egALqGs0Uq8",
            "disabled": false,
            "type": "default"
          }
        ],
        "auth": {
          "type": "noauth"
        },
        "description": "",
        "url": {
          "raw": "http://localhost:8080/tasks",
          "protocol": "http",
          "host": [
            "localhost:8080"
          ],
          "path": [
            "tasks"
          ],
          "query": [],
          "variable": []
        },
        "body": {
          "mode": "raw",
          "raw": "{\n  \"title\": \"FLA\",\n  \"body\": \"Make Task APP with Design Pattern\",\n  \"priority\": \"HIGH\"\n}\n",
          "options": {
            "raw": {
              "language": "json"
            }
          }
        }
      }
    },
    {
      "name": "Get All",
      "request": {
        "method": "GET",
        "header": [
          {
            "key": "Authorization",
            "value": "Bearer eyJhbGciOiJIUzI1NiJ9.eyJzdWIiOiJDaWh1eSIsImlhdCI6MTc3ODQ2NTU1MiwiZXhwIjoxNzc4NTUxOTUyfQ.0OMRlcasvAX7kFG9WANHfsh1nuzPboF7egALqGs0Uq8",
            "disabled": false,
            "type": "default"
          }
        ],
        "auth": {
          "type": "noauth"
        },
        "description": "",
        "url": {
          "raw": "http://localhost:8080/tasks",
          "protocol": "http",
          "host": [
            "localhost:8080"
          ],
          "path": [
            "tasks"
          ],
          "query": [],
          "variable": []
        }
      }
    },
    {
      "name": "Get",
      "request": {
        "method": "GET",
        "header": [
          {
            "key": "Authorization",
            "value": "Bearer eyJhbGciOiJIUzI1NiJ9.eyJzdWIiOiJDaWh1eSIsImlhdCI6MTc3ODQ2NTU1MiwiZXhwIjoxNzc4NTUxOTUyfQ.0OMRlcasvAX7kFG9WANHfsh1nuzPboF7egALqGs0Uq8",
            "disabled": false,
            "type": "default"
          }
        ],
        "auth": {
          "type": "noauth"
        },
        "description": "",
        "url": {
          "raw": "http://localhost:8080/tasks/id/1",
          "protocol": "http",
          "host": [
            "localhost:8080"
          ],
          "path": [
            "tasks",
            "id",
            "1"
          ],
          "query": [],
          "variable": []
        }
      }
    },
    {
      "name": "Search",
      "request": {
        "method": "GET",
        "header": [
          {
            "key": "Authorization",
            "value": "Bearer eyJhbGciOiJIUzI1NiJ9.eyJzdWIiOiJDaWh1eSIsImlhdCI6MTc3ODQ2NTU1MiwiZXhwIjoxNzc4NTUxOTUyfQ.0OMRlcasvAX7kFG9WANHfsh1nuzPboF7egALqGs0Uq8",
            "disabled": false,
            "type": "default"
          }
        ],
        "auth": {
          "type": "noauth"
        },
        "description": "",
        "url": {
          "raw": "http://localhost:8080/tasks/search?keyword=fla",
          "protocol": "http",
          "host": [
            "localhost:8080"
          ],
          "path": [
            "tasks",
            "search"
          ],
          "query": [
            {
              "key": "keyword",
              "value": "fla"
            }
          ],
          "variable": []
        }
      }
    },
    {
      "name": "Update",
      "request": {
        "method": "PUT",
        "header": [
          {
            "key": "Authorization",
            "value": "Bearer eyJhbGciOiJIUzI1NiJ9.eyJzdWIiOiJDaWh1eSIsImlhdCI6MTc3ODQ2NTU1MiwiZXhwIjoxNzc4NTUxOTUyfQ.0OMRlcasvAX7kFG9WANHfsh1nuzPboF7egALqGs0Uq8",
            "disabled": false,
            "type": "default"
          }
        ],
        "auth": {
          "type": "noauth"
        },
        "description": "",
        "url": {
          "raw": "http://localhost:8080/tasks/id/1",
          "protocol": "http",
          "host": [
            "localhost:8080"
          ],
          "path": [
            "tasks",
            "id",
            "1"
          ],
          "query": [],
          "variable": []
        },
        "body": {
          "mode": "raw",
          "raw": "{\n  \"title\": \"FLA\",\n  \"body\": \"Make Task APP with Design Pattern\",\n  \"priority\": \"MEDIUM\"\n}\n",
          "options": {
            "raw": {
              "language": "json"
            }
          }
        }
      }
    },
    {
      "name": "Delete",
      "request": {
        "method": "DELETE",
        "header": [
          {
            "key": "Authorization",
            "value": "Bearer eyJhbGciOiJIUzI1NiJ9.eyJzdWIiOiJDaWh1eSIsImlhdCI6MTc3ODQ2NTU1MiwiZXhwIjoxNzc4NTUxOTUyfQ.0OMRlcasvAX7kFG9WANHfsh1nuzPboF7egALqGs0Uq8",
            "disabled": false,
            "type": "default"
          }
        ],
        "auth": {
          "type": "noauth"
        },
        "description": "",
        "url": {
          "raw": "http://localhost:8080/tasks/id/1",
          "protocol": "http",
          "host": [
            "localhost:8080"
          ],
          "path": [
            "tasks",
            "id",
            "1"
          ],
          "query": [],
          "variable": []
        }
      }
    }
  ],
  "variable": []
}